gemovi/__init__.py
gemovi/common/__init__.py
gemovi/common/constants.py
gemovi/common/dataset.py
gemovi/common/utils.py
gemovi/common/configs/model_defaults.yaml
gemovi/common/configs/test_fact_pcb.yaml
gemovi/common/configs/unrotated.yaml
gemovi/gan/__init__.py
gemovi/gan/models.py
gemovi/gan/train.py
gemovi/gan/trainer.py
gemovi/vae/LICENSE.md
gemovi/vae/README.md
gemovi/vae/__init__.py
gemovi/vae/dataset.py
gemovi/vae/experiment.py
gemovi/vae/requirements.txt
gemovi/vae/train.py
gemovi/vae/utils.py
gemovi/vae/models/__init__.py
gemovi/vae/models/base.py
gemovi/vae/models/beta_vae.py
gemovi/vae/models/dfcvae.py
gemovi/vae/models/mssim_vae.py
gemovi/vae/models/types_.py
gemovi/viz/__init__.py
gemovi/viz/__main__.py
gemovi/viz/base.py
gemovi/viz/gan.py
gemovi/viz/transformer.py
gemovi/viz/tutorial.py
gemovi/viz/vae.py
gemovi/viz/plugins/__init__.py
gemovi/viz/plugins/helpers.py
gemovi/viz/plugins/metadata.py
gemovi/viz/plugins/perturbation.py
gemovi/viz/plugins/popout.py
gemovi/viz/plugins/prediction.py
gemovi/viz/plugins/reencoding.py
gemovi/viz/plugins/roidecoder.py
gemovi/viz/plugins/roiencoder.py
gemovi/viz/plugins/scatterplot.py
gemovi-0.1.3.dist-info/METADATA
gemovi-0.1.3.dist-info/WHEEL
gemovi-0.1.3.dist-info/RECORD
