Metadata-Version: 2.1
Name: gemovi
Version: 0.1.3
Summary: Visualization tool for generative models
Author-email: Nathan Jessurun <ntjessu@gmail.com>
License: MIT
Classifier: Development Status :: 3 - Alpha
Classifier: Intended Audience :: Developers
Classifier: License :: OSI Approved :: MIT License
Classifier: Programming Language :: Python :: 3
Classifier: Topic :: Software Development :: Build Tools
Requires-Python: >=3.8
Requires-Dist: numpy
Requires-Dist: pandas
Requires-Dist: pyqtgraph>=0.13.1
Requires-Dist: pyyaml
Requires-Dist: qtextras>=0.6.6
Requires-Dist: scikit-learn
Requires-Dist: torch
Requires-Dist: torchvision
Provides-Extra: train
Requires-Dist: pytorch-lightning>=1.4; extra == 'train'
